imdb_assetscraper/__init__.py
imdb_assetscraper/imdb_assetscraper.py
imdb_assetscraper-0.7.2.dist-info/licenses/LICENSE
imdb_assetscraper-0.7.2.dist-info/METADATA
imdb_assetscraper-0.7.2.dist-info/WHEEL
imdb_assetscraper-0.7.2.dist-info/top_level.txt
imdb_assetscraper-0.7.2.dist-info/RECORD
