Metadata-Version: 2.4
Name: imdb_assetscraper
Version: 0.7.2
Summary: imdb_assetscraper
Classifier: Programming Language :: Python :: 3
Classifier: License :: OSI Approved :: GNU General Public License (GPL)
Classifier: Operating System :: OS Independent
Requires-Python: >=3.9
License-File: LICENSE
Requires-Dist: beautifulsoup4
Dynamic: license-file
